{
    "configurations": [
        {
            "name": "Mac",
            "includePath": [
                "~/work/ft_select/includes/**",
                "~/work/ft_select/includes/printf/**",
                "~/work/ft_select/includes/libft/**"
            ],
            "defines": [],
            "macFrameworkPath": [
                "/System/Library/Frameworks",
                "/Library/Frameworks"
            ],
            "compilerPath": "/usr/bin/clang",
            "cStandard": "c11",
            "cppStandard": "c++17",
            "intelliSenseMode": "clang-x64"
        }
    ],
    "version": 4
}